perennial/__init__.py
perennial/__main__.py
perennial/__version__.py
perennial/perennial.py
tests/__init__.py
tests/test_perennial.py
perennial-0.1.0.dist-info/LICENSE
perennial-0.1.0.dist-info/METADATA
perennial-0.1.0.dist-info/WHEEL
perennial-0.1.0.dist-info/top_level.txt
perennial-0.1.0.dist-info/RECORD
