Metadata-Version: 2.1
Name: perennial
Version: 0.1.0
Summary: Journaling kit for long-term self-analysis.
Home-page: https://almonds.dev/focus/perennial
Author: Madison Landry
Author-email: mlandry@mit.edu
License: MIT
Classifier: Programming Language :: Python :: 3.9
Classifier: Programming Language :: Python :: 3.10
Classifier: Programming Language :: Python :: 3.11
Classifier: License :: OSI Approved :: MIT License
Classifier: Operating System :: OS Independent
Requires-Python: >=3.9
License-File: LICENSE
Provides-Extra: dev
Requires-Dist: twine ; extra == 'dev'
Requires-Dist: wheel (>=0.36.2) ; extra == 'dev'
Requires-Dist: check-manifest ; extra == 'dev'
Requires-Dist: Sphinx (>=6.1.3) ; extra == 'dev'
Requires-Dist: sphinx-autodoc-typehints ; extra == 'dev'
Requires-Dist: sphinxcontrib-trio ; extra == 'dev'
